http_seekable_file/AsyncSeekableHTTPFile.py
http_seekable_file/__init__.py
http_seekable_file-0.4.0.dist-info/WHEEL
http_seekable_file-0.4.0.dist-info/METADATA
http_seekable_file-0.4.0.dist-info/RECORD
