Metadata-Version: 2.1
Name: http-seekable-file
Version: 0.4.0
Summary: Provides file-like seekable interface for HTTP(S) URLs in sync and async fashion
Author: JuniorJPDJ
Author-email: dev@juniorjpdj.pl
Requires-Python: >=3.6.1,<4.0.0
Classifier: Programming Language :: Python :: 3
Classifier: Programming Language :: Python :: 3.10
Classifier: Programming Language :: Python :: 3.7
Classifier: Programming Language :: Python :: 3.8
Classifier: Programming Language :: Python :: 3.9
Provides-Extra: async
Provides-Extra: sync
Requires-Dist: aiohttp[speedups] (>=3.6,<4.0); extra == "async"
Requires-Dist: asyncio-rlock (>=0.1.0,<0.2.0); extra == "async"
Requires-Dist: asynciobase (>=0.2.0,<0.3.0); extra == "async"
Requires-Dist: requests (>=2.22,<3.0); extra == "sync"
